mkmapdiary/__about__.py
mkmapdiary/__init__.py
mkmapdiary/__main__.py
mkmapdiary/cache.py
mkmapdiary/db.py
mkmapdiary/geoCluster.py
mkmapdiary/gpxCreator.py
mkmapdiary/taskList.py
mkmapdiary/extras/audio.js
mkmapdiary/extras/cross-orange.svg
mkmapdiary/extras/defaults.yaml
mkmapdiary/extras/extra.sass
mkmapdiary/extras/gallery.js
mkmapdiary/extras/geo.js
mkmapdiary/extras/geo.schema.yaml
mkmapdiary/extras/logo-blue.svg
mkmapdiary/extras/logo-white.svg
mkmapdiary/extras/site_config.yaml
mkmapdiary/locale/de/LC_MESSAGES/messages.mo
mkmapdiary/locale/de/LC_MESSAGES/messages.po
mkmapdiary/tasks/__init__.py
mkmapdiary/tasks/audioTask.py
mkmapdiary/tasks/cr2Task.py
mkmapdiary/tasks/dayPageTask.py
mkmapdiary/tasks/galleryTask.py
mkmapdiary/tasks/geojsonTask.py
mkmapdiary/tasks/gpxTask.py
mkmapdiary/tasks/imageTask.py
mkmapdiary/tasks/journalTask.py
mkmapdiary/tasks/markdownTask.py
mkmapdiary/tasks/qstarzTask.py
mkmapdiary/tasks/siteTask.py
mkmapdiary/tasks/tagsTask.py
mkmapdiary/tasks/textTask.py
mkmapdiary/tasks/base/__init__.py
mkmapdiary/tasks/base/baseTask.py
mkmapdiary/tasks/base/exifReader.py
mkmapdiary/tasks/base/geoLookup.py
mkmapdiary/tasks/base/httpRequest.py
mkmapdiary/templates/day_base.j2
mkmapdiary/templates/day_gallery.j2
mkmapdiary/templates/day_journal.j2
mkmapdiary/templates/day_tags.j2
mkmapdiary/templates/index.j2
mkmapdiary/templates/md_text.j2
mkmapdiary/templates/transcript_segment.j2
mkmapdiary/util/__init__.py
mkmapdiary-0.0.1a7.dist-info/METADATA
mkmapdiary-0.0.1a7.dist-info/WHEEL
mkmapdiary-0.0.1a7.dist-info/entry_points.txt
mkmapdiary-0.0.1a7.dist-info/licenses/LICENSE.txt
mkmapdiary-0.0.1a7.dist-info/RECORD
